{"telegram_user_id": "5052599847", "attempt_record_id": "rec8HoMtOXTbUFeRD", "status": "COMPLETED", "score_raw": 0, "score_max": 15, "time_total_seconds": 1, "answers": [{"question_id": "VO-AUTO-PSY_COMPORT_N5-0033", "answer": "B"}, {"question_id": "VO-AUTO-CUL_GENERAL_N3-0086", "answer": "D"}, {"question_id": "VO-AUTO-HIST_CIV_MYTH_N2-0150", "answer": "B"}, {"question_id": "VO-AUTO-TECH_INNOV_N4-0099", "answer": "D"}, {"question_id": "VO-AUTO-HIST_MONDE_N4-0101", "answer": "D"}, {"question_id": "VO-AUTO-HIST_CIV_MYTH_N3-0106", "answer": "D"}, {"question_id": "VO-AUTO-TECH_INNOV_N5-0079", "answer": "D"}, {"question_id": "VO-AUTO-GEO_MONDE_N3-0092", "answer": "A"}, {"question_id": "VO-AUTO-HIST_MONDE_N3-0134", "answer": "A"}, {"question_id": "VO-AUTO-CUL_CINE_FILM_N2-0168", "answer": "D"}, {"question_id": "VO-AUTO-SCI_GENERAL_N5-0086", "answer": "C"}, {"question_id": "VO-AUTO-CUL_CINE_FILM_N1-0183", "answer": "D"}, {"question_id": "VO-AUTO-HIST_MONDE_N4-0001", "answer": "B"}, {"question_id": "VO-AUTO-TECH_INNOV_N4-0014", "answer": "C"}, {"question_id": "VO-AUTO-GEO_MONDE_N1-0154", "answer": "D"}]}